westwallet_api/__init__.py
westwallet_api/client.py
westwallet_api/exceptions.py
westwallet_api/structures.py
westwallet_api-1.1.9.dist-info/LICENSE
westwallet_api-1.1.9.dist-info/METADATA
westwallet_api-1.1.9.dist-info/WHEEL
westwallet_api-1.1.9.dist-info/top_level.txt
westwallet_api-1.1.9.dist-info/RECORD
