Metadata-Version: 2.1
Name: westwallet-api
Version: 1.1.9
Summary: Official WestWallet Public API Python wrapper
Home-page: https://westwallet.io
Author: WestWallet
Author-email: admin@westwallet.io
License: Apache License 2.0
Platform: UNKNOWN
License-File: LICENSE
Requires-Dist: dataclasses (==0.6)
Requires-Dist: requests (==2.22.0)
